regapp_tools/__init__.py
regapp_tools/bwidm_user.py
regapp_tools/bwidmconnection.py
regapp_tools/bwidmtools.py
regapp_tools/config.py
regapp_tools/helpers.py
regapp_tools/parse_args.py
regapp_tools/parse_args_ssh.py
regapp_tools/regapp_tool.py
regapp_tools/ssh_key_retriever.py
regapp_tools/subiss_to_unix.py
regapp_tools-0.2.16.dist-info/LICENSE
regapp_tools-0.2.16.dist-info/METADATA
regapp_tools-0.2.16.dist-info/WHEEL
regapp_tools-0.2.16.dist-info/entry_points.txt
regapp_tools-0.2.16.dist-info/pbr.json
regapp_tools-0.2.16.dist-info/top_level.txt
regapp_tools-0.2.16.dist-info/RECORD
