Metadata-Version: 2.1
Name: regapp-tools
Version: 0.2.16
Summary: Commandline tools to work with the bwIDM regApp (aka LDAP Facade)
Home-page: https://git.scc.kit.edu/feudal/regapp-tools
Author: Marcus Hardt
Author-email: hardt@kit.edu
License: MIT
Project-URL: Bug Tracker, https://git.scc.kit.edu/feudal/regapp-tools/-/issues
Project-URL: Documentation, https://git.scc.kit.edu/feudal/regapp-tools
Platform: UNKNOWN
Classifier: Development Status :: 3 - Alpha
Classifier: Environment :: Console
Classifier: Intended Audience :: Developers
Classifier: Intended Audience :: Information Technology
Classifier: Intended Audience :: Science/Research
Classifier: Intended Audience :: System Administrators
Classifier: License :: OSI Approved :: MIT License
Classifier: Operating System :: OS Independent
Classifier: Natural Language :: English
Classifier: Programming Language :: Python
Classifier: Programming Language :: Python :: 3
Classifier: Topic :: System :: Systems Administration
Classifier: Topic :: System :: Systems Administration :: Authentication/Directory
Classifier: Topic :: Utilities
License-File: LICENSE
Requires-Dist: requests
Requires-Dist: simplejson
